aluControl.v
// ALU Control Unit: determines what ALU operation will be performed
module aluControl(
    input wire [1:0] aluOp, 
    input wire [5:0] funct,
    output reg [3:0] aluControlOp // operation to be performed in ALU unit
);

/**ALU OPS**/
parameter RTYPE = 2'b10; // use funct for alu control
parameter ITYPE = 2'b00; // add
parameter BRANCH = 2'b01; // sub

/**FUNCT CODES FOR R-TYPES**/
parameter r_add = 6'b100000;
parameter r_sub = 6'b100010;
parameter r_and = 6'b100100;
parameter r_or = 6'b100101;
parameter r_nor = 6'b100111;
parameter r_slt = 6'b101010; // set on less than
parameter r_sll = 6'b000000; // shift left
parameter r_srl = 6'b000010; // shift right

/**FUNCTION : ALU CONTROL**/
parameter AND = 4'b0000;
parameter OR = 4'b0001;
parameter NOR = 4'b1100;
parameter ADD = 4'b0010;
parameter SUB = 4'b0110;
parameter SLT = 4'b0111; // set on less than
/**I MADE UP THESE ALU CONTROL CODES FOR SHIFTING. IDK WHAT IS CORRECT/STANDARD.**/
parameter SLL = 4'b0100; // shift left
parameter SRL = 4'b1000; // shift right
/**I MADE UP THESE ALU CONTROL CODES FOR SHIFTING. IDK WHAT IS CORRECT/STANDARD.**/

always @ (*) begin
    case(aluOp)
    RTYPE: begin
        aluControlOp <= funct == r_and ? AND :
                        (funct == r_or ? OR :
                        (funct == r_nor ? NOR :
                        (funct == r_add ? ADD :
                        (funct == r_sub ? SUB :
                        (funct == r_slt ? SLT :
                        (funct == r_sll ? SLL :
                        (funct == r_srl ? SRL : ADD))))))); // default to add. TODO: change default?
    end

    ITYPE: begin
        aluControlOp <= ADD; // same for J-type, though it does not care about ALU
    end

    BRANCH: begin
        aluControlOp <= SUB;
    end

    default: begin
        aluControlOp <= ADD; // default to ADD. TODO: Change this?
    end

    endcase
end


endmodule

control.v
module control (
    input wire [5:0] opcode,
    output reg regDest,
    output reg jump,
    output reg branch,
    output reg memRead,
    output reg memToReg,
    output reg memWrite,
    output reg regWrite,
    // alu controls
    output reg [1:0] aluOp,
    output reg aluSrc
);

parameter RTYPE = 6'h0; // add, sub, and, or, slt

/*I-TYPES*/
parameter ADDI = 6'h8;
parameter BEQ = 6'h4;
parameter BNE = 6'h5;
parameter LW = 6'h23;

/**J-TYPE**/
parameter JUMP = 6'h2;

/*Change control signals depending on current instruction's opcode*/
always @ (opcode) begin
    case (opcode)

    RTYPE: begin
        regDest = 1;
        regWrite = 1;
        aluSrc = 0;
        aluOp = 2'b10; // need funct to determine ALU operation 
        memWrite = 0;
        memRead = 0;
        memToReg = 0;
        jump = 0;
        branch = 0;
    end

    ADDI: begin
        regDest = 0;
        regWrite = 1;
        aluSrc = 1;
        aluOp = 2'b00; // add
        memWrite = 0;
        memRead = 0;
        memToReg = 0;
        jump = 0;
        branch = 0;
    end

    BEQ: begin
        regDest = 0;
        regWrite = 0;
        aluSrc = 0;
        aluOp = 2'b01; // sub
        memWrite = 0;
        memRead = 0;
        memToReg = 0;
        jump = 0;
        branch = 1;
    end

    BNE: begin
        regDest = 0;
        regWrite = 0;
        aluSrc = 0;
        aluOp = 2'b01; // sub
        memWrite = 0;
        memRead = 0;
        memToReg = 0;
        jump = 0;
        branch = 0;
    end

    LW: begin
        regDest = 0;
        regWrite = 1;
        aluSrc = 1;
        aluOp = 2'b00; // add
        memWrite = 0;
        memRead = 1;
        memToReg = 1;
        jump = 0;
        branch = 0;
    end

    JUMP: begin
        regDest = 0;
        regWrite = 0;
        aluSrc = 0;
        aluOp = 2'b00; // don't care
        memWrite = 0;
        memRead = 0;
        memToReg = 0;
        jump = 1;
        branch = 0;
    end

    endcase
end



endmodule

registers.v
/*
32 registers
    - 31 general purpose regs, 1 register containing the value 0

In MIPS Assembly,
symbolic name : number
----------------------
zero : 0 // constant 0
at : 1 // reserved for assembler
v0-v1 : 2-3 // result registers
a0-a3 : 4-7 // argument registers
t0 - t9 : 8-15, 24-25 // temp registers
s0 - s7: 16-12 // saved registers
k0 - k1: 26-27 // kernel registers
gp: 28 // global data pointer
sp: 29 // stack pointer
fp: 30 // frame pointer
ra: 31 // return address
*/
module registers(
    input wire regDest,
    input wire regWrite,
    input wire [31:0] writeData, // only written if regWrite signal is ON
    input wire [4:0] rs, // rs address
    input wire [4:0] rt, // rt address
    input wire [4:0] rd, // rd address; deteremined by regDest
    output reg [31:0] rsData,
    output reg [31:0] rtData
);

reg [31:0] regs [31:0]; // 32 registers, one word each
reg [4:0] writeReg; // address of reg to write to

integer r;
initial begin
    // TODO: Ensure register $0 CANNOT be changed. must stay $zero
    for (r = 0; r < 32; r = r + 1) begin
        regs[r] = 32'b0;
    end
end

always @ (rs, rt) begin
    writeReg = regDest ? rd : rt;

    rsData <= regs[rs];
    rtData <= regs[rt];
end

always @ (writeData) begin
    if (regWrite == 1'b1)
        regs[writeReg] = writeData;
end

endmodule

fetch.v
// Fetch Instruction Block
module fetch (
    input wire [9:0] pc,
    output wire [31:0] inst
);

// TODO: Make address byte-addressable, word-aligned? or is this for data memory?
    // Each address = 8-bit byte
    // Address must be a multiple of 4 to access
reg [31:0] im [0:1023]; // instruction memory

initial begin
    // For testing: Initialize instruction memory with preloaded instructions
    im[0] = 32'h20020005; // addi $2, $0, 5	
    im[1] = 32'h20070003; // addi $7, $0, 3
    im[2] = 32'h00e22025; // or $4, $7, $2	
    im[3] = 32'h00642824; // and $5, $3, $4
    im[4] = 32'h00a42820; // add $5, $5, $4
    im[5] = 32'h0064302a; // slt $6, $3, $4
    im[6] = 32'h2005000a; // addi $5, $0, 10
    im[7] = 32'h00c53820; // add $7, $6, $5
    im[8] = 32'h00e23822; // sub $7, $7, $2
end

assign inst = im[pc];

endmodule

taylor.v
// CPU Top Block
// taylor is a low performance MIPS single-cycle processor
// 1 cycle = 1 ns = 1 instruction
// 4 KB instruction memory = 1000 instructions
module taylor(
    input clk,
    input rst
);

reg [9:0] pc; // 1000 instructions
wire [9:0] nextPc; // next program counter value; currently w/out branching or jumps

reg [31:0] inst; // current instruction
wire [31:0] nextInst; // next instruction; from fetchBlock

/**Instruction fields**/
wire [5:0] opcode;
wire [4:0] rs;
wire [4:0] rt;
wire [4:0] rd;
wire [4:0] shamt;
wire [5:0] funct;
wire [15:0] i_imm;
wire [25:0] j_addr;

assign rs = inst[25:21];
assign rt = inst[20:16];
assign rd = inst[15:11];
assign i_imm = inst[15:0]; // need to sign-extend to 32 bits
assign j_addr = inst[25:0]; // need to perform: (PC + 4[31:28]) << 2 = 32 bits

/**Controller**/
wire [1:0] aluOp;
wire regDest;
wire jump;
wire branch;
wire memRead;
wire memToReg;
wire memWrite;
wire regWrite;

/**ALU Control Unit**/
wire [3:0] aluControlOp;

assign opcode = inst[31:26];
assign funct = inst[5:0];
assign nextPc = pc + 1;

/**Register Unit**/
wire [31:0] writeData;
wire [31:0] rsData;
wire [31:0] rtData;

/**Fetch Instruction**/
fetch fetchBlock(
    .pc(pc),
    .inst(nextInst)
);

/**Register Unit**/
registers regUnit(
    .regDest(regDest),
    .regWrite(regWrite),
    .writeData(writeData),
    .rs(rs),
    .rt(rt),
    .rd(rd),
    .rsData(rsData),
    .rtData(rtData)
);

/**Alter control signals based on instruction**/
control controller(
    .opcode(opcode),
    .aluOp(aluOp)
);

/**ALU Control**/
aluControl aluControlUnit(
    .aluOp(aluOp),
    .funct(funct),
    .aluControlOp(aluControlOp)
);

always @ (posedge(clk)) begin
    if (rst) begin
        pc <= 10'b0;
    end

    else begin
    //$display("[%0d]: Instruction %h, rsData %d, PC %0d ", $time, nextInst, rsData, pc);
    /**Instruction Fetch**/
    inst <= nextInst;

    /**Instruction Decode**/
    /*
    R-type: opcode [31:26], rs[25:21], rt[20:16], rd[15:11], shamt[10:6], funct[5:0]
    I-type: opcode [31:26], rs[25:21], rt[20:16], imm[15:0]
    J-type: opcode [31:26], addr[25:0]
    */
    regUnit.regs[rt] = 32'b1;
    $display("rd, rs, rt number: %b, %b, %b", rd, rs, rt);

    /**Execution**/

    /**Memory Access**/

    /**Writeback**/

    // updating pc
    pc <= nextPc;

    end

end

endmodule

im_tb.v
`timescale 1ns/1ns

module im_tb;

parameter CLK_PERIOD = 10; // ns

// inputs
reg clk;
reg rst;

initial begin
    $dumpfile("test.vcd");
    $dumpvars(0,im_tb);

    $display("im testing.\n");
    taylor.pc = 0;
    clk = 0;

    // ADDI
    taylor.rom[0] = 32'h20100005;
    // ADDI
    taylor.rom[1] = 32'h20100006;
    // ADD
    taylor.rom[2] = 32'h012A4820;
    // SUB
    taylor.rom[3] = 32'h012A4822;
    // SUB
    taylor.rom[4] = 32'h012A4822;
    // BEQ
    taylor.rom[5] = 32'h112A002A;
    // BEQ
    taylor.rom[6] = 32'h112A002B;
    // LOAD WORD
    taylor.rom[7] = 32'h8C0A0000;
    // ORI
    taylor.rom[8] = 32'h34E700FF;    
end

// clk generator
always #((CLK_PERIOD)/2) clk <= ~clk; // 10ns

// Monitor to display current instruction
integer counter = 0;

always @(posedge clk) begin
    if (counter < 9) begin
        //$display("[%0d], PC: %0d, Instruction: %8h", $time, taylor.pc, taylor.inst);
        counter <= counter + 1;
    end
    else begin
        $display("taylor fetching stopped after 14th boyfriend.");
        $finish;
    end
end

taylor taylor(
    .clk(clk),
    .rst(rst)
);

endmodule

test.vcd
$date
	Sun Apr 16 13:22:55 2023
$end
$version
	Icarus Verilog
$end
$timescale
	1ns
$end
$scope module im_tb $end
$var reg 1 ! clk $end
$var reg 1 " rst $end
$var integer 32 # counter [31:0] $end
$scope module taylor $end
$var wire 1 ! clk $end
$var wire 1 $ regDest $end
$var wire 1 % regWrite $end
$var wire 1 " rst $end
$var wire 32 & writeData [31:0] $end
$var wire 32 ' rtData [31:0] $end
$var wire 5 ( rt [4:0] $end
$var wire 32 ) rsData [31:0] $end
$var wire 5 * rs [4:0] $end
$var wire 5 + rd [4:0] $end
$var wire 6 , opcode [5:0] $end
$var wire 10 - nextPc [9:0] $end
$var wire 32 . nextInst [31:0] $end
$var wire 26 / j_addr [25:0] $end
$var wire 16 0 i_imm [15:0] $end
$var wire 6 1 funct [5:0] $end
$var wire 2 2 aluOp [1:0] $end
$var wire 4 3 aluControlOp [3:0] $end
$var reg 32 4 inst [31:0] $end
$var reg 10 5 pc [9:0] $end
$scope module aluControlUnit $end
$var wire 6 6 funct [5:0] $end
$var wire 2 7 aluOp [1:0] $end
$var reg 4 8 aluControlOp [3:0] $end
$upscope $end
$scope module controller $end
$var wire 6 9 opcode [5:0] $end
$var reg 2 : aluOp [1:0] $end
$var reg 1 ; aluSrc $end
$var reg 1 < branch $end
$var reg 1 = jump $end
$var reg 1 > memRead $end
$var reg 1 ? memToReg $end
$var reg 1 @ memWrite $end
$var reg 1 A regDest $end
$var reg 1 B regWrite $end
$upscope $end
$scope module fetchBlock $end
$var wire 32 C inst [31:0] $end
$var wire 10 D pc [9:0] $end
$upscope $end
$scope module regUnit $end
$var wire 5 E rd [4:0] $end
$var wire 1 $ regDest $end
$var wire 1 % regWrite $end
$var wire 5 F rs [4:0] $end
$var wire 5 G rt [4:0] $end
$var wire 32 H writeData [31:0] $end
$var reg 32 I rsData [31:0] $end
$var reg 32 J rtData [31:0] $end
$var reg 5 K writeReg [4:0] $end
$var integer 32 L r [31:0] $end
$upscope $end
$upscope $end
$upscope $end
$enddefinitions $end
#0
$dumpvars
b100000 L
bx K
bx J
bx I
bz H
bx G
bx F
bx E
b0 D
b100000000000100000000000000101 C
xB
xA
x@
x?
x>
x=
x<
x;
bx :
bx 9
bx 8
bx 7
bx 6
b0 5
bx 4
bx 3
bx 2
bx 1
bx 0
bx /
b100000000000100000000000000101 .
b1 -
bx ,
bx +
bx *
bx )
bx (
bx '
bz &
z%
z$
b0 #
0"
0!
$end
#5
b0 '
b0 J
b0 )
b0 I
b10 3
b10 8
b0x0 K
0<
0=
0?
0>
0@
b0 2
b0 7
b0 :
1;
1B
0A
b0 *
b0 F
b10 (
b10 G
b0 +
b0 E
b101 0
b100000000000000101 /
b1000 ,
b1000 9
b101 1
b101 6
b10 -
b100000000001110000000000000011 .
b100000000001110000000000000011 C
b1 5
b1 D
b100000000000100000000000000101 4
b1 #
1!
#10
0!
#15
b0xxx K
b111 (
b111 G
b11 0
b1110000000000000011 /
b11 1
b11 6
b10 #
b11 -
b111000100010000000100101 .
b111000100010000000100101 C
b10 5
b10 D
b100000000001110000000000000011 4
1!
#20
0!
#25
b1 3
b1 8
b1 '
b1 J
b1 )
b1 I
b0xx0 K
b10 2
b10 7
b10 :
0;
1A
b111 *
b111 F
b10 (
b10 G
b100 +
b100 E
b10000000100101 0
b111000100010000000100101 /
b0 ,
b0 9
b100101 1
b100101 6
b100 -
b11001000010100000100100 .
b11001000010100000100100 C
b11 5
b11 D
b111000100010000000100101 4
b11 #
1!
#30
0!
#35
b0 '
b0 J
b0 )
b0 I
b0 3
b0 8
b10x K
b11 *
b11 F
b100 (
b100 G
b101 +
b101 E
b10100000100100 0
b11001000010100000100100 /
b100100 1
b100100 6
b100 #
b101 -
b101001000010100000100000 .
b101001000010100000100000 C
b100 5
b100 D
b11001000010100000100100 4
1!
#40
0!
#45
b1 '
b1 J
b10 3
b10 8
b101 *
b101 F
b10100000100000 0
b101001000010100000100000 /
b100000 1
b100000 6
b110 -
b11001000011000000101010 .
b11001000011000000101010 C
b101 5
b101 D
b101001000010100000100000 4
b101 #
1!
#50
0!
#55
b111 3
b111 8
b1x0 K
b11 *
b11 F
b110 +
b110 E
b11000000101010 0
b11001000011000000101010 /
b101010 1
b101010 6
b110 #
b111 -
b100000000001010000000000001010 .
b100000000001010000000000001010 C
b110 5
b110 D
b11001000011000000101010 4
1!
#60
0!
#65
b0 '
b0 J
b10 3
b10 8
b0x0x K
b0 2
b0 7
b0 :
1;
0A
b0 *
b0 F
b101 (
b101 G
b0 +
b0 E
b1010 0
b1010000000000001010 /
b1000 ,
b1000 9
b1010 1
b1010 6
b1000 -
b110001010011100000100000 .
b110001010011100000100000 C
b111 5
b111 D
b100000000001010000000000001010 4
b111 #
1!
#70
0!
#75
b1 '
b1 J
b1x1 K
b10 2
b10 7
b10 :
0;
1A
b110 *
b110 F
b111 +
b111 E
b11100000100000 0
b110001010011100000100000 /
b0 ,
b0 9
b100000 1
b100000 6
b1000 #
b1001 -
b111000100011100000100010 .
b111000100011100000100010 C
b1000 5
b1000 D
b110001010011100000100000 4
1!
#80
0!
#85
b1 )
b1 I
b110 3
b110 8
b0x1x K
b111 *
b111 F
b10 (
b10 G
b11100000100010 0
b111000100011100000100010 /
b100010 1
b100010 6
b1010 -
bx .
bx C
b1001 5
b1001 D
b111000100011100000100010 4
b1001 #
1!
#90
0!
#95
bx '
bx J
bx )
bx I
bx 3
bx 8
bx K
bx *
bx F
bx (
bx G
bx +
bx E
bx 0
bx /
bx ,
bx 9
bx 1
bx 6
b1011 -
b1010 5
b1010 D
bx 4
1!
