taylor.v
// CPU Top Block
// taylor is a low performance MIPS single-cycle processor
// 1 cycle = 1 ns = 1 instruction
// 4 KB instruction memory = 1000 instructions
module taylor(
    input clk,
    input rst,
    output reg [9:0] pc // 1000 instructions
);

always @(posedge clk) begin
    if (rst) begin
        pc <= 10'b0;
    end
end

reg [31:0] rom [0:1023]; // instruction memory
reg [31:0] inst; // current instruction

/**Instruction types**/
reg [5:0] opcode;
/**
reg [25:21] rs;
reg [20:16] rt;
reg [15:11] rd;
reg [10:6] shamt;
reg [5:0] funct;

reg [15:0] i_imm;

reg [25:0] j_addr;
*/


/**Instruction Fetch**/
always @ (posedge(clk)) begin
    /**Instruction Fetch**/
    inst <= rom[pc];

    /**Instruction Decode, Register Fetch**/
    /*
    R-type: opcode [31:26], rs[25:21], rt[20:16], rd[15:11], shamt[10:6], funct[5:0]
    I-type: opcode [31:26], rs[25:21], rt[20:16], imm[15:0]
    J-type: opcode [31:26], addr[25:0]
    */
    opcode <= rom[pc][31:26];

    $display("T: %0d, PC: %0d, OPCODE: %0h", $time, pc, opcode);

    case (opcode)
    // R-type
    6'h0: begin
        $display("R-Type Instruction: %h\n", inst);
    end
    // addi
    6'h8: begin 
        $display("Addi Instruction: %h\n", inst);
    end
    // addiu
    6'h9: begin
        $display("Addiu Instruction: %h\n", inst);
    end
    // andi
    6'hc: begin
        $display("Andi Instruction: %\n", inst);
    end
    // beq
    6'h4: begin
        $display("Beq Instruction: %h\n", inst);
    end
    // bne
    6'h5: begin
        $display("Addiu Instruction: %h\n", inst);
    end
    // lw
    6'h23: begin
        $display("Lw Instruction: %h\n", inst);
    end
    // ori
    6'hd: begin
        $display("Ori Instruction: %h\n", inst);
    end
    default: $display("ERROR OPCODE %b FROM INST %h\n", opcode, inst);

    endcase

end

endmodule

im_tb.v
`timescale 1ns/1ns

module im_tb;

parameter CLK_PERIOD = 10; // ns

// inputs
reg clk;
reg rst;

initial begin
    $dumpfile("test.vcd");
    $dumpvars(0,im_tb);

    $display("im testing.\n");
    taylor.pc = 0;
    clk = 0;

    // ADDI
    taylor.rom[0] = 32'h20100005;
    // ADDI
    taylor.rom[1] = 32'h20100006;
    // ADD
    taylor.rom[2] = 32'h012A4820;
    // SUB
    taylor.rom[3] = 32'h012A4822;
    // SUB
    taylor.rom[4] = 32'h012A4822;
    // BEQ
    taylor.rom[5] = 32'h112A002A;
    // BEQ
    taylor.rom[6] = 32'h112A002B;
    // LOAD WORD
    taylor.rom[7] = 32'h8C0A0000;
    // ORI
    taylor.rom[8] = 32'h34E700FF;    
end

// clk generator
always #((CLK_PERIOD)/2) clk <= ~clk; // 10ns

// Monitor to display current instruction
integer counter = 0;

always @(posedge clk) begin
    if (counter < 9) begin
        //$display("[%0d], PC: %0d, Instruction: %8h", $time, taylor.pc, taylor.inst);
        taylor.pc <= taylor.pc + 1;
        counter <= counter + 1;
    end
    else begin
        $display("taylor fetching stopped after 14th boyfriend.");
        $finish;
    end
end

taylor taylor(
    .clk(clk),
    .rst(rst)
);

endmodule

test.vcd
$date
	Wed Apr 12 10:23:55 2023
$end
$version
	Icarus Verilog
$end
$timescale
	1ns
$end
$scope module im_tb $end
$var reg 1 ! clk $end
$var reg 1 " rst $end
$var integer 32 # counter [31:0] $end
$scope module taylor $end
$var wire 1 ! clk $end
$var wire 1 " rst $end
$var reg 32 $ inst [31:0] $end
$var reg 6 % opcode [5:0] $end
$var reg 10 & pc [9:0] $end
$upscope $end
$upscope $end
$enddefinitions $end
#0
$dumpvars
b0 &
bx %
bx $
b0 #
x"
0!
$end
#5
b1000 %
b100000000100000000000000000101 $
b1 #
b1 &
1!
#10
0!
#15
b10 #
b10 &
b100000000100000000000000000110 $
1!
#20
0!
#25
b0 %
b1001010100100100000100000 $
b11 #
b11 &
1!
#30
0!
#35
b100 #
b100 &
b1001010100100100000100010 $
1!
#40
0!
#45
b101 #
b101 &
1!
#50
0!
#55
b110 #
b110 &
b100 %
b10001001010100000000000101010 $
1!
#60
0!
#65
b10001001010100000000000101011 $
b111 #
b111 &
1!
#70
0!
#75
b1000 #
b1000 &
b100011 %
b10001100000010100000000000000000 $
1!
#80
0!
#85
b1101 %
b110100111001110000000011111111 $
b1001 #
b1001 &
1!
#90
0!
#95
bx %
bx $
1!
