alu.v
// ALU OPERATIONS
/**
AND = 4'b0000;
OR = 4'b0001;
NOR = 4'b1100;
ADD = 4'b0010;
SUB = 4'b0110;
SLT = 4'b0111; // set on less than
//I MADE UP THESE ALU CONTROL CODES FOR SHIFTING. IDK WHAT IS STANDARD.//
SLL = 4'b0100; // shift left
SRL = 4'b1000; // shift right
//I MADE UP THESE ALU CONTROL CODES FOR SHIFTING. IDK WHAT IS STANDARD.//
**/
module alu (
    // alu control signals
    input wire [3:0] aluControlOp,
    input wire aluSrc, // get from rtData or inst[15:0] sign-extended (imm)
    // data
    input wire [31:0] rsData,
    input wire [31:0] rtData,
    input wire [4:0] shamt,
    input wire [31:0] imm,
    output reg [31:0] result
);

parameter AND = 4'b0000;
parameter OR = 4'b0001;
parameter NOR = 4'b1100;
parameter ADD = 4'b0010;
parameter SUB = 4'b0110;
parameter SLT = 4'b0111; // set on less than
/**I MADE UP THESE ALU CONTROL CODES FOR SHIFTING. IDK WHAT IS STANDARD.**/
parameter SLL = 4'b0100; // shift left
parameter SRL = 4'b1000; // shift right
/**I MADE UP THESE ALU CONTROL CODES FOR SHIFTING. IDK WHAT IS STANDARD.**/

always @ (*) begin
    case(aluControlOp)
    ADD: begin
        result <= aluSrc ? rsData + imm : rsData + rtData; // addi or regular add
    end

    SUB: begin
        result <= rsData - rtData;
    end

    AND: begin
        result <= rsData & rtData; 
    end

    OR: begin
        result <= rsData | rtData;
    end

    NOR: begin
        result <= rsData ~| rtData;
    end

    SLT: begin
        result <= rsData < rtData;
    end

    SLL: begin
        result <= rtData << shamt;
    end

    SRL: begin
        result <= rtData >> shamt;
    end
endcase
end


endmodule

aluControl.v
// ALU Control Unit: determines what ALU operation will be performed
module aluControl(
    input wire [1:0] aluOp, 
    input wire [5:0] funct,
    output reg [3:0] aluControlOp // operation to be performed in ALU unit
);

/**ALU OPS**/
parameter RTYPE = 2'b10; // use funct for alu control
parameter ITYPE = 2'b00; // add
parameter BRANCH = 2'b01; // sub

/**FUNCT CODES FOR R-TYPES**/
parameter r_add = 6'b100000;
parameter r_sub = 6'b100010;
parameter r_and = 6'b100100;
parameter r_or = 6'b100101;
parameter r_nor = 6'b100111;
parameter r_slt = 6'b101010; // set on less than
parameter r_sll = 6'b000000; // shift left
parameter r_srl = 6'b000010; // shift right

/**FUNCTION : ALU CONTROL**/
parameter AND = 4'b0000;
parameter OR = 4'b0001;
parameter NOR = 4'b1100;
parameter ADD = 4'b0010;
parameter SUB = 4'b0110;
parameter SLT = 4'b0111; // set on less than
/**I MADE UP THESE ALU CONTROL CODES FOR SHIFTING. IDK WHAT IS STANDARD.**/
parameter SLL = 4'b0100; // shift left
parameter SRL = 4'b1000; // shift right
/**I MADE UP THESE ALU CONTROL CODES FOR SHIFTING. IDK WHAT IS STANDARD.**/

always @ (*) begin
    case(aluOp)
    RTYPE: begin
        aluControlOp <= funct == r_and ? AND :
                        (funct == r_or ? OR :
                        (funct == r_nor ? NOR :
                        (funct == r_add ? ADD :
                        (funct == r_sub ? SUB :
                        (funct == r_slt ? SLT :
                        (funct == r_sll ? SLL :
                        (funct == r_srl ? SRL : ADD))))))); // default to add. TODO: change default?
    end

    ITYPE: begin
        aluControlOp <= ADD; // same for J-type, though it does not care about ALU
    end

    BRANCH: begin
        aluControlOp <= SUB;
    end

    default: begin
        aluControlOp <= ADD; // default to ADD. TODO: Change this?
    end

    endcase
end


endmodule

control.v
module control (
    input wire [5:0] opcode,
    output reg regDest,
    output reg jump,
    output reg branch,
    output reg memRead,
    output reg memToReg,
    output reg memWrite,
    output reg regWrite,
    // alu controls
    output reg [1:0] aluOp,
    output reg aluSrc
);

parameter RTYPE = 6'h0; // add, sub, and, or, slt

/*I-TYPES*/
parameter ADDI = 6'h8;
parameter BEQ = 6'h4;
parameter BNE = 6'h5;
parameter LW = 6'h23;

/**J-TYPE**/
parameter JUMP = 6'h2;

/*Change control signals depending on current instruction's opcode*/
always @ (opcode) begin
    case (opcode)

    RTYPE: begin
        regDest = 1;
        regWrite = 1;
        aluSrc = 0;
        aluOp = 2'b10; // need funct to determine ALU operation 
        memWrite = 0;
        memRead = 0;
        memToReg = 0;
        jump = 0;
        branch = 0;
    end

    ADDI: begin
        regDest = 0;
        regWrite = 1;
        aluSrc = 1;
        aluOp = 2'b00; // add
        memWrite = 0;
        memRead = 0;
        memToReg = 0;
        jump = 0;
        branch = 0;
    end

    BEQ: begin
        regDest = 0;
        regWrite = 0;
        aluSrc = 0;
        aluOp = 2'b01; // sub
        memWrite = 0;
        memRead = 0;
        memToReg = 0;
        jump = 0;
        branch = 1;
    end

    BNE: begin
        regDest = 0;
        regWrite = 0;
        aluSrc = 0;
        aluOp = 2'b01; // sub
        memWrite = 0;
        memRead = 0;
        memToReg = 0;
        jump = 0;
        branch = 0;
    end

    LW: begin
        regDest = 0;
        regWrite = 1;
        aluSrc = 1;
        aluOp = 2'b00; // add
        memWrite = 0;
        memRead = 1;
        memToReg = 1;
        jump = 0;
        branch = 0;
    end

    JUMP: begin
        regDest = 0;
        regWrite = 0;
        aluSrc = 0;
        aluOp = 2'b00; // don't care
        memWrite = 0;
        memRead = 0;
        memToReg = 0;
        jump = 1;
        branch = 0;
    end

    endcase
end



endmodule

registers.v
/*
32 registers
    - 31 general purpose regs, 1 register containing the value 0

In MIPS Assembly,
symbolic name : number
----------------------
zero : 0 // constant 0
at : 1 // reserved for assembler
v0-v1 : 2-3 // result registers
a0-a3 : 4-7 // argument registers
t0 - t9 : 8-15, 24-25 // temp registers
s0 - s7: 16-12 // saved registers
k0 - k1: 26-27 // kernel registers
gp: 28 // global data pointer
sp: 29 // stack pointer
fp: 30 // frame pointer
ra: 31 // return address
*/
module registers(
    input wire regDest,
    input wire regWrite,
    input wire [31:0] writeData, // only written if regWrite signal is ON
    input wire [4:0] rs, // rs address
    input wire [4:0] rt, // rt address
    input wire [4:0] rd, // rd address; deteremined by regDest
    output reg [31:0] rsData,
    output reg [31:0] rtData
);

reg [31:0] regs [31:0]; // 32 registers, one word each
reg [4:0] writeReg; // address of reg to write to

integer r;
initial begin
    // TODO: Ensure register $0 CANNOT be changed. must stay $zero
    for (r = 0; r < 32; r = r + 1) begin
        regs[r] = 32'b0;
    end
end

always @ (rs, rt) begin
    writeReg = regDest ? rd : rt;

    rsData <= regs[rs];
    rtData <= regs[rt];
end

always @ (writeData) begin
    if (regWrite == 1'b1)
        regs[writeReg] = writeData;
end

endmodule

fetch.v
// Fetch Instruction Block
module fetch (
    input wire [9:0] pc,
    output wire [31:0] inst
);

// TODO: Make address byte-addressable, word-aligned? or is this for data memory?
    // Each address = 8-bit byte
    // Address must be a multiple of 4 to access
reg [31:0] im [0:1023]; // instruction memory

initial begin
    // For testing: Initialize instruction memory with preloaded instructions
    im[0] = 32'h20020005; // addi $2, $0, 5	-- $v0 = 5
    im[1] = 32'h20070003; // addi $7, $0, 3 -- $a3 = 3
    im[2] = 32'h20840003; // addi $4, $0, 3 -- $a0 = 3             
    im[3] = 32'h00e22025; // or $4, $7, $2 -- $a0 = $v0 or $a0 = 3
    im[4] = 32'h00642824; // and $5, $3, $4 -- $a1 = $v1 and $a0 = 0
    im[5] = 32'h00a42820; // add $5, $5, $4 -- $a1 = $a1 + $a0 = 3
    im[6] = 32'h0064302a; // slt $6, $3, $4 -- 
    im[7] = 32'h2005000a; // addi $5, $0, 10 -- 
    im[8] = 32'h00c53820; // add $7, $6, $5 -- 
    im[9] = 32'h00e23822; // sub $7, $7, $2 -- 
end

assign inst = im[pc];

endmodule

taylor.v
// CPU Top Block
// taylor is a low performance MIPS single-cycle processor
// 1 cycle = 1 ns = 1 instruction
// 4 KB instruction memory = 1000 instructions
module taylor(
    input clk,
    input rst
);

reg [9:0] pc; // 1000 instructions
wire [9:0] nextPc; // next program counter value; currently w/out branching or jumps

reg [31:0] inst; // current instruction
wire [31:0] nextInst; // next instruction; from fetchBlock

/**Instruction fields**/
wire [5:0] opcode;
wire [4:0] rs;
wire [4:0] rt;
wire [4:0] rd;
wire [4:0] shamt;
wire [5:0] funct;
wire [15:0] i_imm;
wire [31:0] i_extImm;
wire [25:0] j_addr;

assign rs = inst[25:21];
assign rt = inst[20:16];
assign rd = inst[15:11];
assign i_imm = inst[15:0];
assign i_extImm = $signed(i_imm);
assign j_addr = inst[25:0]; // need to perform: (PC + 4[31:28]) << 2 = 32 bits

/**Controller**/
wire [1:0] aluOp;
wire aluSrc;
wire regDest;
wire jump;
wire branch;
wire memRead;
wire memToReg;
wire memWrite;
wire regWrite;

/**ALU Control Unit**/
wire [3:0] aluControlOp;

assign opcode = inst[31:26];
assign funct = inst[5:0];
assign nextPc = pc + 1;

/**Register Unit**/
wire [31:0] writeData;
wire [31:0] rsData;
wire [31:0] rtData;

/**ALU Unit**/
wire [31:0] aluResult;

/**Fetch Instruction**/
fetch fetchBlock(
    .pc(pc),
    .inst(nextInst)
);

/**Register Unit**/
registers regUnit(
    .regDest(regDest),
    .regWrite(regWrite),
    .writeData(writeData),
    .rs(rs),
    .rt(rt),
    .rd(rd),
    .rsData(rsData),
    .rtData(rtData)
);

/**Alter control signals based on instruction**/
control controller(
    .opcode(opcode),
    .aluOp(aluOp),
    .aluSrc(aluSrc),
    .regDest(regDest),
    .jump(jump),
    .branch(branch),
    .memRead(memRead),
    .memToReg(memToReg),
    .memWrite(memWrite),
    .regWrite(regWrite)
);

/**ALU Control**/
aluControl aluControlUnit(
    .aluOp(aluOp),
    .funct(funct),
    .aluControlOp(aluControlOp)
);

/**ALU**/
alu aluUnit(
    .aluControlOp(aluControlOp),
    .aluSrc(aluSrc),
    .rsData(rsData),
    .rtData(rtData),
    .shamt(shamt),
    .imm(i_extImm),
    .result(aluResult)
);

always @ (posedge(clk)) begin
    if (rst) begin
        pc <= 10'b0;
    end

    else begin
    //$display("[%0d]: Instruction %h, rsData %d, PC %0d ", $time, nextInst, rsData, pc);
    /**Instruction Fetch**/
    inst <= nextInst;

    /**Instruction Decode**/
    /*
    R-type: opcode [31:26], rs[25:21], rt[20:16], rd[15:11], shamt[10:6], funct[5:0]
    I-type: opcode [31:26], rs[25:21], rt[20:16], imm[15:0]
    J-type: opcode [31:26], addr[25:0]
    */
    $display("rd, rs, rt, result number: %b, %b, %b, %0d", rd, rs, rt, aluResult);

    /**Execution**/

    /**Memory Access**/

    /**Writeback**/

    // updating pc
    pc <= nextPc;

    end

end

endmodule

im_tb.v
`timescale 1ns/1ns

module im_tb;

parameter CLK_PERIOD = 10; // ns

// inputs
reg clk;
reg rst;

initial begin
    $dumpfile("test.vcd");
    $dumpvars(0,im_tb);

    $display("im testing.\n");
    taylor.pc = 0;
    clk = 0;

    // ADDI
    taylor.rom[0] = 32'h20100005;
    // ADDI
    taylor.rom[1] = 32'h20100006;
    // ADD
    taylor.rom[2] = 32'h012A4820;
    // SUB
    taylor.rom[3] = 32'h012A4822;
    // SUB
    taylor.rom[4] = 32'h012A4822;
    // BEQ
    taylor.rom[5] = 32'h112A002A;
    // BEQ
    taylor.rom[6] = 32'h112A002B;
    // LOAD WORD
    taylor.rom[7] = 32'h8C0A0000;
    // ORI
    taylor.rom[8] = 32'h34E700FF;    
end

// clk generator
always #((CLK_PERIOD)/2) clk <= ~clk; // 10ns

// Monitor to display current instruction
integer counter = 0;

always @(posedge clk) begin
    if (counter < 9) begin
        //$display("[%0d], PC: %0d, Instruction: %8h", $time, taylor.pc, taylor.inst);
        counter <= counter + 1;
    end
    else begin
        $display("taylor fetching stopped after 14th boyfriend.");
        $finish;
    end
end

taylor taylor(
    .clk(clk),
    .rst(rst)
);

endmodule

test.vcd
$date
	Sun Apr 16 20:07:55 2023
$end
$version
	Icarus Verilog
$end
$timescale
	1ns
$end
$scope module im_tb $end
$var reg 1 ! clk $end
$var reg 1 " rst $end
$var integer 32 # counter [31:0] $end
$scope module taylor $end
$var wire 1 ! clk $end
$var wire 1 " rst $end
$var wire 5 $ shamt [4:0] $end
$var wire 32 % writeData [31:0] $end
$var wire 32 & rtData [31:0] $end
$var wire 5 ' rt [4:0] $end
$var wire 32 ( rsData [31:0] $end
$var wire 5 ) rs [4:0] $end
$var wire 1 * regWrite $end
$var wire 1 + regDest $end
$var wire 5 , rd [4:0] $end
$var wire 6 - opcode [5:0] $end
$var wire 10 . nextPc [9:0] $end
$var wire 32 / nextInst [31:0] $end
$var wire 1 0 memWrite $end
$var wire 1 1 memToReg $end
$var wire 1 2 memRead $end
$var wire 1 3 jump $end
$var wire 26 4 j_addr [25:0] $end
$var wire 16 5 i_imm [15:0] $end
$var wire 32 6 i_extImm [31:0] $end
$var wire 6 7 funct [5:0] $end
$var wire 1 8 branch $end
$var wire 1 9 aluSrc $end
$var wire 32 : aluResult [31:0] $end
$var wire 2 ; aluOp [1:0] $end
$var wire 4 < aluControlOp [3:0] $end
$var reg 32 = inst [31:0] $end
$var reg 10 > pc [9:0] $end
$scope module aluControlUnit $end
$var wire 6 ? funct [5:0] $end
$var wire 2 @ aluOp [1:0] $end
$var reg 4 A aluControlOp [3:0] $end
$upscope $end
$scope module aluUnit $end
$var wire 4 B aluControlOp [3:0] $end
$var wire 32 C imm [31:0] $end
$var wire 5 D shamt [4:0] $end
$var wire 32 E rtData [31:0] $end
$var wire 32 F rsData [31:0] $end
$var wire 1 9 aluSrc $end
$var reg 32 G result [31:0] $end
$upscope $end
$scope module controller $end
$var wire 6 H opcode [5:0] $end
$var reg 2 I aluOp [1:0] $end
$var reg 1 9 aluSrc $end
$var reg 1 8 branch $end
$var reg 1 3 jump $end
$var reg 1 2 memRead $end
$var reg 1 1 memToReg $end
$var reg 1 0 memWrite $end
$var reg 1 + regDest $end
$var reg 1 * regWrite $end
$upscope $end
$scope module fetchBlock $end
$var wire 32 J inst [31:0] $end
$var wire 10 K pc [9:0] $end
$upscope $end
$scope module regUnit $end
$var wire 5 L rd [4:0] $end
$var wire 1 + regDest $end
$var wire 1 * regWrite $end
$var wire 5 M rs [4:0] $end
$var wire 5 N rt [4:0] $end
$var wire 32 O writeData [31:0] $end
$var reg 32 P rsData [31:0] $end
$var reg 32 Q rtData [31:0] $end
$var reg 5 R writeReg [4:0] $end
$var integer 32 S r [31:0] $end
$upscope $end
$upscope $end
$upscope $end
$enddefinitions $end
#0
$dumpvars
b100000 S
bx R
bx Q
bx P
bz O
bx N
bx M
bx L
b0 K
b100000000000100000000000000101 J
bx I
bx H
bx G
bx F
bx E
bz D
bx C
bx B
bx A
bx @
bx ?
b0 >
bx =
bx <
bx ;
bx :
x9
x8
bx 7
bx 6
bx 5
bx 4
x3
x2
x1
x0
b100000000000100000000000000101 /
b1 .
bx -
bx ,
x+
x*
bx )
bx (
bx '
bx &
bz %
bz $
b0 #
0"
0!
$end
#5
b101 :
b101 G
b0 &
b0 E
b0 Q
b0 (
b0 F
b0 P
b10 <
b10 A
b10 B
b10 R
08
03
01
02
00
b0 ;
b0 @
b0 I
19
1*
0+
b0 )
b0 M
b10 '
b10 N
b0 ,
b0 L
b101 6
b101 C
b101 5
b100000000000000101 4
b1000 -
b1000 H
b101 7
b101 ?
b10 .
b100000000001110000000000000011 /
b100000000001110000000000000011 J
b1 >
b1 K
b100000000000100000000000000101 =
b1 #
1!
#10
0!
#15
b11 :
b11 G
b111 R
b111 '
b111 N
b11 6
b11 C
b11 5
b1110000000000000011 4
b11 7
b11 ?
b10 #
b11 .
b100000100001000000000000000011 /
b100000100001000000000000000011 J
b10 >
b10 K
b100000000001110000000000000011 =
1!
#20
0!
#25
b100 R
b100 )
b100 M
b100 '
b100 N
b100001000000000000000011 4
b100 .
b111000100010000000100101 /
b111000100010000000100101 J
b11 >
b11 K
b100000100001000000000000000011 =
b11 #
1!
#30
0!
#35
b1 <
b1 A
b1 B
b0 :
b0 G
b10 ;
b10 @
b10 I
09
1+
b111 )
b111 M
b10 '
b10 N
b100 ,
b100 L
b10000000100101 6
b10000000100101 C
b10000000100101 5
b111000100010000000100101 4
b0 -
b0 H
b100101 7
b100101 ?
b100 #
b101 .
b11001000010100000100100 /
b11001000010100000100100 J
b100 >
b100 K
b111000100010000000100101 =
1!
#40
0!
#45
b0 <
b0 A
b0 B
b101 R
b11 )
b11 M
b100 '
b100 N
b101 ,
b101 L
b10100000100100 6
b10100000100100 C
b10100000100100 5
b11001000010100000100100 4
b100100 7
b100100 ?
b110 .
b101001000010100000100000 /
b101001000010100000100000 J
b101 >
b101 K
b11001000010100000100100 =
b101 #
1!
#50
0!
#55
b10 <
b10 A
b10 B
b101 )
b101 M
b10100000100000 6
b10100000100000 C
b10100000100000 5
b101001000010100000100000 4
b100000 7
b100000 ?
b110 #
b111 .
b11001000011000000101010 /
b11001000011000000101010 J
b110 >
b110 K
b101001000010100000100000 =
1!
#60
0!
#65
b111 <
b111 A
b111 B
b110 R
b11 )
b11 M
b110 ,
b110 L
b11000000101010 6
b11000000101010 C
b11000000101010 5
b11001000011000000101010 4
b101010 7
b101010 ?
b1000 .
b100000000001010000000000001010 /
b100000000001010000000000001010 J
b111 >
b111 K
b11001000011000000101010 =
b111 #
1!
#70
0!
#75
b1010 :
b1010 G
b10 <
b10 A
b10 B
b101 R
b0 ;
b0 @
b0 I
19
0+
b0 )
b0 M
b101 '
b101 N
b0 ,
b0 L
b1010 6
b1010 C
b1010 5
b1010000000000001010 4
b1000 -
b1000 H
b1010 7
b1010 ?
b1000 #
b1001 .
b110001010011100000100000 /
b110001010011100000100000 J
b1000 >
b1000 K
b100000000001010000000000001010 =
1!
#80
0!
#85
b0 :
b0 G
b111 R
b10 ;
b10 @
b10 I
09
1+
b110 )
b110 M
b111 ,
b111 L
b11100000100000 6
b11100000100000 C
b11100000100000 5
b110001010011100000100000 4
b0 -
b0 H
b100000 7
b100000 ?
b1010 .
b111000100011100000100010 /
b111000100011100000100010 J
b1001 >
b1001 K
b110001010011100000100000 =
b1001 #
1!
#90
0!
#95
b110 <
b110 A
b110 B
b111 )
b111 M
b10 '
b10 N
b11100000100010 6
b11100000100010 C
b11100000100010 5
b111000100011100000100010 4
b100010 7
b100010 ?
b1011 .
bx /
bx J
b1010 >
b1010 K
b111000100011100000100010 =
1!
