aluControl.v
// ALU Control Unit: determines what ALU operation will be performed
module aluControl(
    input wire [1:0] aluOp, 
    input wire [5:0] funct,
    output reg [3:0] aluControlOp // operation to be performed in ALU unit
);

/**ALU OPS**/
parameter RTYPE = 2'b10; // use funct for alu control
parameter ITYPE = 2'b00; // add
parameter BRANCH = 2'b01; // sub

/**FUNCT CODES FOR R-TYPES**/
parameter r_add = 6'b100000;
parameter r_sub = 6'b100010;
parameter r_and = 6'b100100;
parameter r_or = 6'b100101;
parameter r_nor = 6'b100111;
parameter r_slt = 6'b101010; // set on less than
parameter r_sll = 6'b000000; // shift left
parameter r_srl = 6'b000010; // shift right

/**FUNCTION : ALU CONTROL**/
parameter AND = 4'b0000;
parameter OR = 4'b0001;
parameter NOR = 4'b1100;
parameter ADD = 4'b0010;
parameter SUB = 4'b0110;
parameter SLT = 4'b0111; // set on less than
/**I MADE UP THESE ALU CONTROL CODES FOR SHIFTING. IDK WHAT IS CORRECT/STANDARD.**/
parameter SLL = 4'b0100; // shift left
parameter SRL = 4'b1000; // shift right
/**I MADE UP THESE ALU CONTROL CODES FOR SHIFTING. IDK WHAT IS CORRECT/STANDARD.**/

always @ (*) begin
    case(aluOp)
    RTYPE: begin
        aluControlOp <= funct == r_and ? AND :
                        (funct == r_or ? OR :
                        (funct == r_nor ? NOR :
                        (funct == r_add ? ADD :
                        (funct == r_sub ? SUB :
                        (funct == r_slt ? SLT :
                        (funct == r_sll ? SLL :
                        (funct == r_srl ? SRL : ADD))))))); // default to add. TODO: change default?
    end

    ITYPE: begin
        aluControlOp <= ADD; // same for J-type, though it does not care about ALU
    end

    BRANCH: begin
        aluControlOp <= SUB;
    end

    default: begin
        aluControlOp <= ADD; // default to ADD. TODO: Change this?
    end

    endcase
end


endmodule

control.v
module control (
    input wire [5:0] opcode,
    output reg regDest,
    output reg jump,
    output reg branch,
    output reg memRead,
    output reg memToReg,
    output reg memWrite,
    output reg regWrite,
    // alu controls
    output reg [1:0] aluOp,
    output reg aluSrc
);

parameter RTYPE = 6'h0; // add, sub, and, or, slt

/*I-TYPES*/
parameter ADDI = 6'h8;
parameter BEQ = 6'h4;
parameter BNE = 6'h5;
parameter LW = 6'h23;

/**J-TYPE**/
parameter JUMP = 6'h2;

/*Change control signals depending on current instruction's opcode*/
always @ (opcode) begin
    case (opcode)

    RTYPE: begin
        regDest = 1;
        regWrite = 1;
        aluSrc = 0;
        aluOp = 2'b10; // need funct to determine ALU operation 
        memWrite = 0;
        memRead = 0;
        memToReg = 0;
        jump = 0;
        branch = 0;
    end

    ADDI: begin
        regDest = 0;
        regWrite = 1;
        aluSrc = 1;
        aluOp = 2'b00; // add
        memWrite = 0;
        memRead = 0;
        memToReg = 0;
        jump = 0;
        branch = 0;
    end

    BEQ: begin
        regDest = 0;
        regWrite = 0;
        aluSrc = 0;
        aluOp = 2'b01; // sub
        memWrite = 0;
        memRead = 0;
        memToReg = 0;
        jump = 0;
        branch = 1;
    end

    BNE: begin
        regDest = 0;
        regWrite = 0;
        aluSrc = 0;
        aluOp = 2'b01; // sub
        memWrite = 0;
        memRead = 0;
        memToReg = 0;
        jump = 0;
        branch = 0;
    end

    LW: begin
        regDest = 0;
        regWrite = 1;
        aluSrc = 1;
        aluOp = 2'b00; // add
        memWrite = 0;
        memRead = 1;
        memToReg = 1;
        jump = 0;
        branch = 0;
    end

    JUMP: begin
        regDest = 0;
        regWrite = 0;
        aluSrc = 0;
        aluOp = 2'b00; // don't care
        memWrite = 0;
        memRead = 0;
        memToReg = 0;
        jump = 1;
        branch = 0;
    end

    endcase
end



endmodule

registers.v
/*
32 registers
    - 31 general purpose regs, 1 register containing the value 0

In MIPS Assembly,
symbolic name : number
----------------------
zero : 0 // constant 0
at : 1 // reserved for assembler
v0-v1 : 2-3 // result registers
a0-a3 : 4-7 // argument registers
t0 - t9 : 8-15, 24-25 // temp registers
s0 - s7: 16-12 // saved registers
k0 - k1: 26-27 // kernel registers
gp: 28 // global data pointer
sp: 29 // stack pointer
fp: 30 // frame pointer
ra: 31 // return address
*/
module registers(
    input wire regDest,
    input wire regWrite,

    input wire [31:0] writeData, // only written if regWrite signal is ON
    inout wire [31:0] rsData, // reg1 data
    inout wire [31:0] rtData, // reg2 data
    input wire [4:0] rd // dest reg; determined by regDest
);




endmodule

fetch.v
// Fetch Instruction Block
module fetch (
    input wire [9:0] pc,
    output wire [31:0] inst
);

// TODO: Make address byte-addressable, word-aligned? or is this for data memory?
    // Each address = 8-bit byte
    // Address must be a multiple of 4 to access
reg [31:0] im [0:1023]; // instruction memory

initial begin
    // Initialize instruction memory with preloaded instructions
    im[0] = 32'h20100001; // ADDI
    im[1] = 32'h012A4820; // ADD
    im[2] = 32'h20100006; // ADDI
    im[3] = 32'h012A4822; // SUB
    im[4] = 32'h112A002A; // BEQ
    im[5] = 32'h012A4822; // SUB
    im[6] = 32'h112A002B; // BEQ
    im[7] = 32'h8C0A0000; // LOAD WORD
    im[8] = 32'h8C0A0000; // LOAD WORD
end

assign inst = im[pc];

endmodule

taylor.v
// CPU Top Block
// taylor is a low performance MIPS single-cycle processor
// 1 cycle = 1 ns = 1 instruction
// 4 KB instruction memory = 1000 instructions
module taylor(
    input clk,
    input rst
);

reg [9:0] pc; // 1000 instructions
wire [9:0] nextPc; // next program counter value; currently w/out branching or jumps

reg [31:0] inst; // current instruction
wire [31:0] nextInst; // next instruction; from fetchBlock

/**Instruction fields**/
wire [5:0] opcode;
wire [4:0] rs;
wire [4:0] rt;
wire [4:0] rd;
wire [4:0] shamt;
wire [5:0] funct;
wire [15:0] i_imm;
wire [25:0] j_addr;

assign rs = inst[25:21];
assign rt = inst[20:16];
assign rd = inst[15:11];
assign i_imm = inst[15:0]; // need to sign-extend to 32 bits
assign j_addr = inst[25:0]; // need to perform: (PC + 4[31:28]) << 2 = 32 bits

/**Controller**/
wire [1:0] aluOp;
wire regDest;
wire jump;
wire branch;
wire memRead;
wire memToReg;
wire memWrite;
wire regWrite;

/**ALU Control Unit**/
wire [3:0] aluControlOp;

assign opcode = inst[31:26];
assign funct = inst[5:0];
assign nextPc = pc + 1;

/**Register Unit**/
wire [31:0] writeData;
wire [31:0] rsData;
wire [31:0] rtData;
wire [4:0] regRd; // dest address

assign rsData = pc[rs];
assign rtData = pc[rt];

/**Fetch Instruction**/
fetch fetchBlock(
    .pc(pc),
    .inst(nextInst)
);

/**Register Unit**/
registers regUnit(
    .regDest(regDest),
    .regWrite(regWrite),
    .writeData(writeData),
    .rsData(rsData),
    .rtData(rtData),
    .rd(regRd)
);

/**Alter control signals based on instruction**/
control controller(
    .opcode(opcode),
    .aluOp(aluOp)
);

/**ALU Control**/
aluControl aluControlUnit(
    .aluOp(aluOp),
    .funct(funct),
    .aluControlOp(aluControlOp)
);

always @ (posedge(clk)) begin
    if (rst) begin
        pc <= 10'b0;
    end

    else begin
    $display("[%0d]: Instruction %h, PC %0d", $time, nextInst, pc);
    /**Instruction Fetch**/
    inst <= nextInst;

    /**Instruction Decode**/
    /*
    R-type: opcode [31:26], rs[25:21], rt[20:16], rd[15:11], shamt[10:6], funct[5:0]
    I-type: opcode [31:26], rs[25:21], rt[20:16], imm[15:0]
    J-type: opcode [31:26], addr[25:0]
    */



    /**Execution**/

    /**Memory Access**/

    /**Writeback**/

    // updating pc
    pc <= nextPc;

    end

end

endmodule

im_tb.v
`timescale 1ns/1ns

module im_tb;

parameter CLK_PERIOD = 10; // ns

// inputs
reg clk;
reg rst;

initial begin
    $dumpfile("test.vcd");
    $dumpvars(0,im_tb);

    $display("im testing.\n");
    taylor.pc = 0;
    clk = 0;

    // ADDI
    taylor.rom[0] = 32'h20100005;
    // ADDI
    taylor.rom[1] = 32'h20100006;
    // ADD
    taylor.rom[2] = 32'h012A4820;
    // SUB
    taylor.rom[3] = 32'h012A4822;
    // SUB
    taylor.rom[4] = 32'h012A4822;
    // BEQ
    taylor.rom[5] = 32'h112A002A;
    // BEQ
    taylor.rom[6] = 32'h112A002B;
    // LOAD WORD
    taylor.rom[7] = 32'h8C0A0000;
    // ORI
    taylor.rom[8] = 32'h34E700FF;    
end

// clk generator
always #((CLK_PERIOD)/2) clk <= ~clk; // 10ns

// Monitor to display current instruction
integer counter = 0;

always @(posedge clk) begin
    if (counter < 9) begin
        //$display("[%0d], PC: %0d, Instruction: %8h", $time, taylor.pc, taylor.inst);
        counter <= counter + 1;
    end
    else begin
        $display("taylor fetching stopped after 14th boyfriend.");
        $finish;
    end
end

taylor taylor(
    .clk(clk),
    .rst(rst)
);

endmodule

test.vcd
$date
	Thu Apr 13 18:05:35 2023
$end
$version
	Icarus Verilog
$end
$timescale
	1ns
$end
$scope module im_tb $end
$var reg 1 ! clk $end
$var reg 1 " rst $end
$var integer 32 # counter [31:0] $end
$scope module taylor $end
$var wire 1 ! clk $end
$var wire 1 $ regDest $end
$var wire 5 % regRd [4:0] $end
$var wire 1 & regWrite $end
$var wire 1 " rst $end
$var wire 32 ' writeData [31:0] $end
$var wire 32 ( rtData [31:0] $end
$var wire 5 ) rt [4:0] $end
$var wire 32 * rsData [31:0] $end
$var wire 5 + rs [4:0] $end
$var wire 5 , rd [4:0] $end
$var wire 6 - opcode [5:0] $end
$var wire 10 . nextPc [9:0] $end
$var wire 32 / nextInst [31:0] $end
$var wire 26 0 j_addr [25:0] $end
$var wire 16 1 i_imm [15:0] $end
$var wire 6 2 funct [5:0] $end
$var wire 2 3 aluOp [1:0] $end
$var wire 4 4 aluControlOp [3:0] $end
$var reg 32 5 inst [31:0] $end
$var reg 10 6 pc [9:0] $end
$scope module aluControlUnit $end
$var wire 6 7 funct [5:0] $end
$var wire 2 8 aluOp [1:0] $end
$var reg 4 9 aluControlOp [3:0] $end
$upscope $end
$scope module controller $end
$var wire 6 : opcode [5:0] $end
$var reg 2 ; aluOp [1:0] $end
$var reg 1 < aluSrc $end
$var reg 1 = branch $end
$var reg 1 > jump $end
$var reg 1 ? memRead $end
$var reg 1 @ memToReg $end
$var reg 1 A memWrite $end
$var reg 1 B regDest $end
$var reg 1 C regWrite $end
$upscope $end
$scope module fetchBlock $end
$var wire 32 D inst [31:0] $end
$var wire 10 E pc [9:0] $end
$upscope $end
$scope module regUnit $end
$var wire 5 F rd [4:0] $end
$var wire 1 $ regDest $end
$var wire 1 & regWrite $end
$var wire 32 G rsData [31:0] $end
$var wire 32 H rtData [31:0] $end
$var wire 32 I writeData [31:0] $end
$upscope $end
$upscope $end
$upscope $end
$enddefinitions $end
#0
$dumpvars
bz I
b0x H
b0x G
bz F
b0 E
b100000000100000000000000000001 D
xC
xB
xA
x@
x?
x>
x=
x<
bx ;
bx :
bx 9
bx 8
bx 7
b0 6
bx 5
bx 4
bx 3
bx 2
bx 1
bx 0
b100000000100000000000000000001 /
b1 .
bx -
bx ,
bx +
b0x *
bx )
b0x (
bz '
z&
bz %
z$
b0 #
0"
0!
$end
#5
b10 4
b10 9
0=
0>
0@
0?
0A
b0 3
b0 8
b0 ;
1<
1C
0B
b1 *
b1 G
b0 +
b10000 )
b0 ,
b1 1
b100000000000000000001 0
b1000 -
b1000 :
b1 2
b1 7
b10 .
b1001010100100100000100000 /
b1001010100100100000100000 D
b1 6
b1 E
b100000000100000000000000000001 5
b1 #
1!
#10
0!
#15
b10 3
b10 8
b10 ;
0<
1B
b1001 +
b1010 )
b1001 ,
b100100000100000 1
b1001010100100100000100000 0
b0 -
b0 :
b100000 2
b100000 7
b10 #
b11 .
b0 *
b0 G
b100000000100000000000000000110 /
b100000000100000000000000000110 D
b10 6
b10 E
b1001010100100100000100000 5
1!
#20
0!
#25
b0 3
b0 8
b0 ;
1<
0B
b1 *
b1 G
b0 +
b10000 )
b0 ,
b110 1
b100000000000000000110 0
b1000 -
b1000 :
b110 2
b110 7
b100 .
b1001010100100100000100010 /
b1001010100100100000100010 D
b11 6
b11 E
b100000000100000000000000000110 5
b11 #
1!
#30
0!
#35
b110 4
b110 9
b10 3
b10 8
b10 ;
0<
1B
b1001 +
b1010 )
b1001 ,
b100100000100010 1
b1001010100100100000100010 0
b0 -
b0 :
b100010 2
b100010 7
b100 #
b101 .
b0 *
b0 G
b10001001010100000000000101010 /
b10001001010100000000000101010 D
b100 6
b100 E
b1001010100100100000100010 5
1!
#40
0!
#45
1=
b1 3
b1 8
b1 ;
0C
0B
b0 ,
b101010 1
b1001010100000000000101010 0
b100 -
b100 :
b101010 2
b101010 7
b110 .
b1001010100100100000100010 /
b1001010100100100000100010 D
b101 6
b101 E
b10001001010100000000000101010 5
b101 #
1!
#50
0!
#55
0=
b10 3
b10 8
b10 ;
1C
1B
b1001 ,
b100100000100010 1
b1001010100100100000100010 0
b0 -
b0 :
b100010 2
b100010 7
b110 #
b111 .
b10001001010100000000000101011 /
b10001001010100000000000101011 D
b110 6
b110 E
b1001010100100100000100010 5
1!
#60
0!
#65
1=
b1 3
b1 8
b1 ;
0C
0B
b0 ,
b101011 1
b1001010100000000000101011 0
b100 -
b100 :
b101011 2
b101011 7
b1000 .
b10001100000010100000000000000000 /
b10001100000010100000000000000000 D
b111 6
b111 E
b10001001010100000000000101011 5
b111 #
1!
#70
0!
#75
b10 4
b10 9
0=
1@
1?
b0 3
b0 8
b0 ;
1<
1C
b0 +
b0 1
b10100000000000000000 0
b100011 -
b100011 :
b0 2
b0 7
b1000 #
b1001 .
b1000 6
b1000 E
b10001100000010100000000000000000 5
1!
#80
0!
#85
b1010 .
b1 *
b1 G
bx /
bx D
b1001 6
b1001 E
b1001 #
1!
#90
0!
#95
bx +
bx )
bx ,
bx 1
bx 0
bx -
bx :
bx 2
bx 7
b1011 .
b0x *
b0x G
b1010 6
b1010 E
bx 5
1!
