control.v
module control (
    input wire [5:0] opcode,
    output reg regDest,
    output reg jump,
    output reg branch,
    output reg memRead,
    output reg memToReg,
    output reg memWrite,
    output reg regWrite,
    // alu controls
    output reg [1:0] aluOp,
    output reg aluSrc
);

parameter RTYPE = 6'h0; // add, sub, and, or, slt
    parameter ADD = 2'b00;
    parameter SUB = 2'b01;

/*I-TYPES*/
parameter ADDI = 6'h8;
parameter BEQ = 6'h4;
parameter BNE = 6'h5;
parameter LW = 6'h23;

/**J-TYPE**/
parameter JUMP = 6'h2;

/*Change control signals depending on current instruction's opcode*/
always @ (opcode) begin
    case (opcode)

    RTYPE: begin
        regDest = 1;
        regWrite = 1;
        aluSrc = 0;
        aluOp = 2'b10; // need funct to determine ALU operation 
        memWrite = 0;
        memRead = 0;
        memToReg = 0;
        jump = 0;
        branch = 0;
        $display("RTYPE INSTRUCTION");
    end

    ADDI: begin
        regDest = 0;
        regWrite = 1;
        aluSrc = 1;
        aluOp = 2'b00; // add
        memWrite = 0;
        memRead = 0;
        memToReg = 0;
        jump = 0;
        branch = 0;
        $display("ADDI INSTRUCTION");
    end

    BEQ: begin
        regDest = 0;
        regWrite = 0;
        aluSrc = 0;
        aluOp = 2'b01; // sub
        memWrite = 0;
        memRead = 0;
        memToReg = 0;
        jump = 0;
        branch = 1;
        $display("BEQ INSTRUCTION");
    end

    BNE: begin
        regDest = 0;
        regWrite = 0;
        aluSrc = 0;
        aluOp = 2'b01; // sub
        memWrite = 0;
        memRead = 0;
        memToReg = 0;
        jump = 0;
        branch = 0;
        $display("BNE INSTRUCTION");
    end

    LW: begin
        regDest = 0;
        regWrite = 1;
        aluSrc = 1;
        aluOp = 2'b00; // add
        memWrite = 0;
        memRead = 1;
        memToReg = 1;
        jump = 0;
        branch = 0;
        $display("LW INSTRUCTION");
    end

    JUMP: begin
        regDest = 0;
        regWrite = 0;
        aluSrc = 0;
        aluOp = 2'b00; // don't care
        memWrite = 0;
        memRead = 0;
        memToReg = 0;
        jump = 1;
        branch = 0;
        $display("JUMP INSTRUCTION");
    end

    endcase
end



endmodule

fetch.v
// Fetch Instruction Block
module fetch (
    input wire [9:0] pc,
    output wire [31:0] inst
);

// TODO: Make address byte-addressable, word-aligned? or is this for data memory?
    // Each address = 8-bit byte
    // Address must be a multiple of 4 to access
reg [31:0] im [0:1023]; // instruction memory

initial begin
    // Initialize instruction memory with preloaded instructions
    // THIS SHIT DOESNT WORK. NEED TO CHANGE INSTRUCTIONS...
    im[0] = 32'h2004001b; // ADDI
    im[1] = 32'h2005001B; // ADDI
    im[2] = 32'h00853020; // ADD
    im[3] = 32'h00a43822; // SUB
    im[4] = 32'h00e6402a; // SLT
    im[5] = 32'h00e04825; // OR
    im[6] = 32'h00e05024; // AND
    im[7] = 32'h00075840; // SLL
    im[8] = 32'h00076042; // SRL
end

assign inst = im[pc];

endmodule

taylor.v
// CPU Top Block
// taylor is a low performance MIPS single-cycle processor
// 1 cycle = 1 ns = 1 instruction
// 4 KB instruction memory = 1000 instructions
module taylor(
    input clk,
    input rst
);

reg [9:0] pc; // 1000 instructions
wire [9:0] nextPc; // next program counter value; currently w/out branching or jumps

reg [31:0] inst; // current instruction
wire [31:0] nextInst; // next instruction; from fetchBlock

/**Instruction fields**/
wire [5:0] opcode;
wire [4:0] rs;
wire [4:0] rt;
wire [4:0] rd;
wire [4:0] shamt;
wire [5:0] funct;
wire [15:0] i_imm;
wire [25:0] j_addr;

assign opcode = inst[31:26];
assign funct = inst[5:0];
assign nextPc = pc + 1;

/**Fetch Instruction**/
fetch fetchBlock (
    .pc(pc),
    .inst(nextInst)
);

/**Alter control signals based on instruction**/
control controller(
    .opcode(opcode)
);

always @ (posedge(clk)) begin
    if (rst) begin
        pc <= 10'b0;
    end

    else begin
    $display("[%0d]: Instruction %h, PC %0d", $time, nextInst, pc);
    /**Instruction Fetch**/
    inst <= nextInst;

    /**Instruction Decode**/
    /*
    R-type: opcode [31:26], rs[25:21], rt[20:16], rd[15:11], shamt[10:6], funct[5:0]
    I-type: opcode [31:26], rs[25:21], rt[20:16], imm[15:0]
    J-type: opcode [31:26], addr[25:0]
    */


    /**Execution**/

    /**Memory Access**/

    /**Writeback**/

    // updating pc
    pc <= nextPc;

    end

end

endmodule

im_tb.v
`timescale 1ns/1ns

module im_tb;

parameter CLK_PERIOD = 10; // ns

// inputs
reg clk;
reg rst;

initial begin
    $dumpfile("test.vcd");
    $dumpvars(0,im_tb);

    $display("im testing.\n");
    taylor.pc = 0;
    clk = 0;

    // ADDI
    taylor.rom[0] = 32'h20100005;
    // ADDI
    taylor.rom[1] = 32'h20100006;
    // ADD
    taylor.rom[2] = 32'h012A4820;
    // SUB
    taylor.rom[3] = 32'h012A4822;
    // SUB
    taylor.rom[4] = 32'h012A4822;
    // BEQ
    taylor.rom[5] = 32'h112A002A;
    // BEQ
    taylor.rom[6] = 32'h112A002B;
    // LOAD WORD
    taylor.rom[7] = 32'h8C0A0000;
    // ORI
    taylor.rom[8] = 32'h34E700FF;    
end

// clk generator
always #((CLK_PERIOD)/2) clk <= ~clk; // 10ns

// Monitor to display current instruction
integer counter = 0;

always @(posedge clk) begin
    if (counter < 9) begin
        //$display("[%0d], PC: %0d, Instruction: %8h", $time, taylor.pc, taylor.inst);
        counter <= counter + 1;
    end
    else begin
        $display("taylor fetching stopped after 14th boyfriend.");
        $finish;
    end
end

taylor taylor(
    .clk(clk),
    .rst(rst)
);

endmodule

test.vcd
$date
	Wed Apr 12 22:29:09 2023
$end
$version
	Icarus Verilog
$end
$timescale
	1ns
$end
$scope module im_tb $end
$var reg 1 ! clk $end
$var reg 1 " rst $end
$var integer 32 # counter [31:0] $end
$scope module taylor $end
$var wire 1 ! clk $end
$var wire 1 " rst $end
$var wire 6 $ opcode [5:0] $end
$var wire 10 % nextPc [9:0] $end
$var wire 32 & nextInst [31:0] $end
$var wire 6 ' funct [5:0] $end
$var reg 32 ( inst [31:0] $end
$var reg 10 ) pc [9:0] $end
$scope module controller $end
$var wire 6 * opcode [5:0] $end
$var reg 2 + aluOp [1:0] $end
$var reg 1 , aluSrc $end
$var reg 1 - branch $end
$var reg 1 . jump $end
$var reg 1 / memRead $end
$var reg 1 0 memToReg $end
$var reg 1 1 memWrite $end
$var reg 1 2 regDest $end
$var reg 1 3 regWrite $end
$upscope $end
$scope module fetchBlock $end
$var wire 32 4 inst [31:0] $end
$var wire 10 5 pc [9:0] $end
$upscope $end
$upscope $end
$upscope $end
$enddefinitions $end
#0
$dumpvars
b0 5
b100000000100000000000000000001 4
x3
x2
x1
x0
x/
x.
x-
x,
bx +
bx *
b0 )
bx (
bx '
b100000000100000000000000000001 &
b1 %
bx $
b0 #
0"
0!
$end
#5
0-
0.
00
0/
01
b0 +
1,
13
02
b1000 $
b1000 *
b1 '
b10 %
b1001010100100100000100000 &
b1001010100100100000100000 4
b1 )
b1 5
b100000000100000000000000000001 (
b1 #
1!
#10
0!
#15
b10 +
0,
12
b0 $
b0 *
b100000 '
b10 #
b11 %
b100000000100000000000000000110 &
b100000000100000000000000000110 4
b10 )
b10 5
b1001010100100100000100000 (
1!
#20
0!
#25
b0 +
1,
02
b1000 $
b1000 *
b110 '
b100 %
b1001010100100100000100010 &
b1001010100100100000100010 4
b11 )
b11 5
b100000000100000000000000000110 (
b11 #
1!
#30
0!
#35
b10 +
0,
12
b0 $
b0 *
b100010 '
b100 #
b101 %
b10001001010100000000000101010 &
b10001001010100000000000101010 4
b100 )
b100 5
b1001010100100100000100010 (
1!
#40
0!
#45
1-
b1 +
03
02
b100 $
b100 *
b101010 '
b110 %
b1001010100100100000100010 &
b1001010100100100000100010 4
b101 )
b101 5
b10001001010100000000000101010 (
b101 #
1!
#50
0!
#55
0-
b10 +
13
12
b0 $
b0 *
b100010 '
b110 #
b111 %
b10001001010100000000000101011 &
b10001001010100000000000101011 4
b110 )
b110 5
b1001010100100100000100010 (
1!
#60
0!
#65
1-
b1 +
03
02
b100 $
b100 *
b101011 '
b1000 %
b10001100000010100000000000000000 &
b10001100000010100000000000000000 4
b111 )
b111 5
b10001001010100000000000101011 (
b111 #
1!
#70
0!
#75
0-
10
1/
b0 +
1,
13
b100011 $
b100011 *
b0 '
b1000 #
b1001 %
b1000 )
b1000 5
b10001100000010100000000000000000 (
1!
#80
0!
#85
b1010 %
bx &
bx 4
b1001 )
b1001 5
b1001 #
1!
#90
0!
#95
bx $
bx *
bx '
b1011 %
b1010 )
b1010 5
bx (
1!
