fetch.v
// Fetch Instruction Block
module fetch (
    input wire [9:0] pc,
    output wire [31:0] inst
);

reg [31:0] rom [0:1023]; // instruction memory

initial begin
    // Initialize instruction memory with preloaded instructions
    rom[0] = 32'h20100001; // ADDI
    rom[1] = 32'h20100006; // ADDI
    rom[2] = 32'h012A4820; // ADD
    rom[3] = 32'h012A4822; // SUB
    rom[4] = 32'h012A4822; // SUB
    rom[5] = 32'h112A002A; // BEQ
    rom[6] = 32'h112A002B; // BEQ
    rom[7] = 32'h8C0A0000; // LOAD WORD
    rom[8] = 32'h34E700FF; // ORI
end

assign inst = rom[pc];

endmodule

taylor.v
// CPU Top Block
// taylor is a low performance MIPS single-cycle processor
// 1 cycle = 1 ns = 1 instruction
// 4 KB instruction memory = 1000 instructions
module taylor(
    input clk,
    input rst
);

reg [9:0] pc; // 1000 instructions
wire [9:0] nextPc;

reg [31:0] inst; // current instruction
wire [31:0] nextInst; // next instruction; from fetchBlock

/**Instruction fields**/
wire [5:0] opcode;
wire [4:0] rs;
wire [4:0] rt;
wire [4:0] rd;
wire [4:0] shamt;
wire [5:0] funct;

wire [15:0] i_imm;

wire [25:0] j_addr;

assign nextPc = pc + 1;

fetch fetchBlock (
    .pc(pc),
    .inst(nextInst)
);

always @ (posedge(clk)) begin
    if (rst) begin
        pc <= 10'b0;
    end

    else begin
    /**Instruction Fetch**/
    inst <= nextInst;
    /**Instruction Decode, Register Fetch**/
    /*
    R-type: opcode [31:26], rs[25:21], rt[20:16], rd[15:11], shamt[10:6], funct[5:0]
    I-type: opcode [31:26], rs[25:21], rt[20:16], imm[15:0]
    J-type: opcode [31:26], addr[25:0]
    */

    /**Execution**/

    /**Memory Access**/

    /**Writeback**/

    pc <= nextPc;

    end

end

endmodule

im_tb.v
`timescale 1ns/1ns

module im_tb;

parameter CLK_PERIOD = 10; // ns

// inputs
reg clk;
reg rst;

initial begin
    $dumpfile("test.vcd");
    $dumpvars(0,im_tb);

    $display("im testing.\n");

    rst = 0;
    clk = 0;

    taylor.pc = 0;

end

// clk generator
always #((CLK_PERIOD)/2) clk <= ~clk; // 10ns

// Monitor to display current instruction
integer counter = 0;

always @(posedge clk) begin
    if (counter < 9) begin
        //$display("[%0d], PC: %0d, Instruction: %8h", $time, taylor.pc, taylor.inst);
        counter <= counter + 1;
    end
    else begin
        $display("taylor fetching stopped.");
        $finish;
    end
end

taylor taylor(
    .clk(clk),
    .rst(rst)
);

endmodule

test.vcd
$date
	Wed Apr 12 19:23:43 2023
$end
$version
	Icarus Verilog
$end
$timescale
	1ns
$end
$scope module im_tb $end
$var reg 1 ! clk $end
$var reg 1 " rst $end
$var integer 32 # counter [31:0] $end
$scope module taylor $end
$var wire 1 ! clk $end
$var wire 1 " rst $end
$var wire 10 $ nextPc [9:0] $end
$var wire 32 % nextInst [31:0] $end
$var reg 32 & inst [31:0] $end
$var reg 10 ' pc [9:0] $end
$scope module fetchBlock $end
$var wire 32 ( inst [31:0] $end
$var wire 10 ) pc [9:0] $end
$upscope $end
$upscope $end
$upscope $end
$enddefinitions $end
#0
$dumpvars
b0 )
b100000000100000000000000000001 (
b0 '
bx &
b100000000100000000000000000001 %
b1 $
b0 #
0"
0!
$end
#5
b10 $
b100000000100000000000000000110 %
b100000000100000000000000000110 (
b1 '
b1 )
b100000000100000000000000000001 &
b1 #
1!
#10
0!
#15
b10 #
b11 $
b1001010100100100000100000 %
b1001010100100100000100000 (
b10 '
b10 )
b100000000100000000000000000110 &
1!
#20
0!
#25
b100 $
b1001010100100100000100010 %
b1001010100100100000100010 (
b11 '
b11 )
b1001010100100100000100000 &
b11 #
1!
#30
0!
#35
b100 #
b101 $
b100 '
b100 )
b1001010100100100000100010 &
1!
#40
0!
#45
b110 $
b10001001010100000000000101010 %
b10001001010100000000000101010 (
b101 '
b101 )
b101 #
1!
#50
0!
#55
b110 #
b111 $
b10001001010100000000000101011 %
b10001001010100000000000101011 (
b110 '
b110 )
b10001001010100000000000101010 &
1!
#60
0!
#65
b1000 $
b10001100000010100000000000000000 %
b10001100000010100000000000000000 (
b111 '
b111 )
b10001001010100000000000101011 &
b111 #
1!
#70
0!
#75
b1000 #
b1001 $
b110100111001110000000011111111 %
b110100111001110000000011111111 (
b1000 '
b1000 )
b10001100000010100000000000000000 &
1!
#80
0!
#85
b1010 $
bx %
bx (
b1001 '
b1001 )
b110100111001110000000011111111 &
b1001 #
1!
#90
0!
#95
b1011 $
b1010 '
b1010 )
bx &
1!
